nterm/__init__.py
nterm/cli.py
nterm/config.py
nterm/enhancedagent.py
nterm/secure_key_manager.py
nterm-0.4.0.dist-info/licenses/LICENSE
tests/__init__.py
tests/test_agent.py
nterm-0.4.0.dist-info/METADATA
nterm-0.4.0.dist-info/WHEEL
nterm-0.4.0.dist-info/entry_points.txt
nterm-0.4.0.dist-info/top_level.txt
nterm-0.4.0.dist-info/RECORD
