Metadata-Version: 2.4
Name: nterm
Version: 0.4.0
Summary: A reasoning agent with system administration and IoT capabilities
Home-page: https://github.com/Neural-Nirvana/nterm
Author: Neural Nirvana
Author-email: Neural Nirvana <ekansh@duck.com>
License: MIT
Project-URL: Homepage, https://github.com/Neural-Nirvana/nterm
Project-URL: Repository, https://github.com/Neural-Nirvana/nterm.git
Project-URL: Issues, https://github.com/Neural-Nirvana/nterm/issues
Keywords: AI,agent,reasoning,system-administration,iot,cli,terminal,reasoning-agent,system-administration-agent,iot-agent,nterm
Classifier: Development Status :: 3 - Alpha
Classifier: Intended Audience :: Developers
Classifier: License :: OSI Approved :: MIT License
Classifier: Operating System :: OS Independent
Classifier: Programming Language :: Python :: 3
Classifier: Programming Language :: Python :: 3.8
Classifier: Programming Language :: Python :: 3.9
Classifier: Programming Language :: Python :: 3.10
Classifier: Programming Language :: Python :: 3.11
Classifier: Topic :: Software Development :: Libraries :: Python Modules
Classifier: Topic :: System :: Systems Administration
Requires-Python: >=3.8
License-File: LICENSE
Requires-Dist: agno
Requires-Dist: openai
Requires-Dist: sqlalchemy
Requires-Dist: qrcode
Requires-Dist: requests
Requires-Dist: cryptography
Provides-Extra: dev
Requires-Dist: pytest; extra == "dev"
Requires-Dist: pytest-cov; extra == "dev"
Dynamic: author
Dynamic: home-page
Dynamic: license-file
Dynamic: requires-python
